mix_gamma_vi/__init__.py
mix_gamma_vi/core.py
mix_gamma_vi-0.0.1.dist-info/LICENSE
mix_gamma_vi-0.0.1.dist-info/METADATA
mix_gamma_vi-0.0.1.dist-info/WHEEL
mix_gamma_vi-0.0.1.dist-info/top_level.txt
mix_gamma_vi-0.0.1.dist-info/RECORD
