Metadata-Version: 2.1
Name: mix-gamma-vi
Version: 0.0.1
Summary: A small example package
Home-page: https://github.com/IsaacBreen/MixGammaVI
Author: Isaac Breen
Author-email: isaac.breen@icloud.com
License: UNKNOWN
Platform: UNKNOWN
Classifier: Programming Language :: Python :: 3
Classifier: License :: OSI Approved :: MIT License
Classifier: Operating System :: OS Independent
Requires-Python: >=3.6
Requires-Dist: tensorflow (>=2)
Requires-Dist: tensorflow-probability (>=0.8)
Requires-Dist: numpy
